Metadata-Version: 2.1
Name: terrace
Version: 0.0.91
Summary: high level PyTorch utils
Home-page: https://github.com/mixarcid/terrace
Author: Michael Brocidiacono
Author-email: 
Classifier: Programming Language :: Python :: 3
Classifier: Operating System :: OS Independent
Requires-Python: >=3.6
License-File: LICENSE.txt
